<!-- Logback configuration. See http://logback.qos.ch/manual/index.html -->
<configuration scan="true" scanPeriod="120 seconds" debug="true">

    <conversionRule conversionWord="nanos"
                    converterClass="com.baifendian.swordfish.common.utils.NanoSampleConverter"/>

    <!-- Simple file output -->
    <appender name="FILE" class="ch.qos.logback.core.rolling.RollingFileAppender">
        <encoder>
            <pattern>
                [%level][%nanos] %date{yyyy-MM-dd HH:mm:ss.SSS} %logger{96}:[%line] - %msg%n
            </pattern>
            <charset>UTF-8</charset> <!-- 此处设置字符集 -->
        </encoder>

        <rollingPolicy class="ch.qos.logback.core.rolling.SizeAndTimeBasedRollingPolicy">
            <!-- rollover daily -->
            <fileNamePattern>logs/exec-server-%d{yyyy-MM-dd}.%i.log</fileNamePattern>
            <maxFileSize>128MB</maxFileSize>
            <maxHistory>14</maxHistory>
            <totalSizeCap>6GB</totalSizeCap>
        </rollingPolicy>
        <!-- Log level filter -->
        <filter class="ch.qos.logback.classic.filter.ThresholdFilter">
            <level>INFO</level>
        </filter>
        <!-- Safely log to the same file from multiple JVMs. Degrades performance! -->
        <prudent>true</prudent>
    </appender>

    <!-- Console output -->
    <appender name="STDOUT" class="ch.qos.logback.core.ConsoleAppender">
        <!-- encoder defaults to ch.qos.logback.classic.encoder.PatternLayoutEncoder -->
        <encoder>
            <pattern>
                [ %level][%nanos] %date{yyyy-MM-dd HH:mm:ss.SSS} %logger{96}:%line - %msg%n
            </pattern>
            <charset>UTF-8</charset> <!-- 此处设置字符集 -->
        </encoder>
        <!-- Log level filter -->
        <filter class="ch.qos.logback.classic.filter.ThresholdFilter">
            <level>DEBUG</level>
        </filter>
    </appender>

    <!-- Enable FILE and STDOUT appenders for all log messages. -->
    <root level="TRACE">
        <appender-ref ref="FILE"/>
        <!--<appender-ref ref="STDOUT"/>-->
    </root>

</configuration>